qwen_token_counter/__init__.py
qwen_token_counter/tokenizer_files/merges.txt
qwen_token_counter/tokenizer_files/tokenizer.json
qwen_token_counter/tokenizer_files/tokenizer_config.json
qwen_token_counter/tokenizer_files/vocab.json
qwen_token_counter-0.2.1.dist-info/licenses/LICENSE
qwen_token_counter-0.2.1.dist-info/METADATA
qwen_token_counter-0.2.1.dist-info/WHEEL
qwen_token_counter-0.2.1.dist-info/top_level.txt
qwen_token_counter-0.2.1.dist-info/RECORD
