Metadata-Version: 2.4
Name: qwen_token_counter
Version: 0.2.1
Summary: A simple token counter for Qwen model series
Home-page: https://github.com/benoqtr/qwen_token_counter
Author: benoqtr
Author-email: benoqtr@gmail.com
Classifier: Programming Language :: Python :: 3
Classifier: License :: OSI Approved :: MIT License
Classifier: Operating System :: OS Independent
Requires-Python: >=3.7
License-File: LICENSE
Requires-Dist: transformers>=4.51.0
Requires-Dist: huggingface-hub>=0.19.0
Dynamic: author
Dynamic: author-email
Dynamic: classifier
Dynamic: description
Dynamic: description-content-type
Dynamic: home-page
Dynamic: license-file
Dynamic: requires-dist
Dynamic: requires-python
Dynamic: summary
